myfirstpackageinfinit/__init__.py
myfirstpackageinfinit/funcs.py
myfirstpackageinfinit-0.0.2.dist-info/METADATA
myfirstpackageinfinit-0.0.2.dist-info/WHEEL
myfirstpackageinfinit-0.0.2.dist-info/top_level.txt
myfirstpackageinfinit-0.0.2.dist-info/RECORD
