Metadata-Version: 2.1
Name: myfirstpackageinfinit
Version: 0.0.2
Summary: Azure Python library
Author: Infinity Team
Keywords: rabbitmq,messaging,queue,producer,consumer
Classifier: Programming Language :: Python :: 3
Classifier: License :: OSI Approved :: MIT License
Classifier: Operating System :: OS Independent
Requires-Python: >=3.6
